<annotation>
  <folder></folder>
  <filename>00001201-PHOTO-2020-12-10-11-47-26.jpg</filename>
  <source>
    <database>Unknown</database>
    <annotation>Unknown</annotation>
    <image>Unknown</image>
  </source>
  <size>
    <width>576</width>
    <height>1024</height>
    <depth></depth>
  </size>
  <segmented>0</segmented>
  <object>
    <name>0</name>
    <occluded>0</occluded>
    <bndbox>
      <xmin>284.23</xmin>
      <ymin>220.23</ymin>
      <xmax>299.19</xmax>
      <ymax>247.51</ymax>
    </bndbox>
  </object>
  <object>
    <name>1</name>
    <occluded>0</occluded>
    <bndbox>
      <xmin>236.13</xmin>
      <ymin>221.11</ymin>
      <xmax>242.87</xmax>
      <ymax>245.75</ymax>
    </bndbox>
  </object>
  <object>
    <name>9</name>
    <occluded>0</occluded>
    <bndbox>
      <xmin>242.58</xmin>
      <ymin>221.11</ymin>
      <xmax>256.95</xmax>
      <ymax>246.33</ymax>
    </bndbox>
  </object>
  <object>
    <name>5</name>
    <occluded>0</occluded>
    <bndbox>
      <xmin>257.25</xmin>
      <ymin>221.99</ymin>
      <xmax>270.2</xmax>
      <ymax>247.51</ymax>
    </bndbox>
  </object>
  <object>
    <name>6</name>
    <occluded>0</occluded>
    <bndbox>
      <xmin>270.45</xmin>
      <ymin>221.99</ymin>
      <xmax>283.94</xmax>
      <ymax>246.92</ymax>
    </bndbox>
  </object>
  <object>
    <name>X</name>
    <occluded>0</occluded>
    <bndbox>
      <xmin>310.63</xmin>
      <ymin>219.64</ymin>
      <xmax>318.26</xmax>
      <ymax>234.6</ymax>
    </bndbox>
  </object>
  <object>
    <name>X</name>
    <occluded>0</occluded>
    <bndbox>
      <xmin>318.55</xmin>
      <ymin>223.45</ymin>
      <xmax>328.23</xmax>
      <ymax>234.89</ymax>
    </bndbox>
  </object>
  <object>
    <name>odometer</name>
    <occluded>0</occluded>
    <bndbox>
      <xmin>196.09</xmin>
      <ymin>201.24</ymin>
      <xmax>359.79</xmax>
      <ymax>280.33</ymax>
    </bndbox>
  </object>
  <object>
    <name>1</name>
    <occluded>0</occluded>
    <bndbox>
      <xmin>220.87</xmin>
      <ymin>220.52</ymin>
      <xmax>230.26</xmax>
      <ymax>246.0</ymax>
    </bndbox>
  </object>
</annotation>
