<annotation>
  <folder></folder>
  <filename>00000685-PHOTO-2020-12-02-17-31-21.jpg</filename>
  <source>
    <database>Unknown</database>
    <annotation>Unknown</annotation>
    <image>Unknown</image>
  </source>
  <size>
    <width>768</width>
    <height>1024</height>
    <depth></depth>
  </size>
  <segmented>0</segmented>
  <object>
    <name>X</name>
    <occluded>0</occluded>
    <bndbox>
      <xmin>457.19</xmin>
      <ymin>506.4</ymin>
      <xmax>478.12</xmax>
      <ymax>527.33</ymax>
    </bndbox>
  </object>
  <object>
    <name>X</name>
    <occluded>0</occluded>
    <bndbox>
      <xmin>238.85</xmin>
      <ymin>449.55</ymin>
      <xmax>264.31</xmax>
      <ymax>498.38</ymax>
    </bndbox>
  </object>
  <object>
    <name>X</name>
    <occluded>0</occluded>
    <bndbox>
      <xmin>267.1</xmin>
      <ymin>461.06</ymin>
      <xmax>293.26</xmax>
      <ymax>498.03</ymax>
    </bndbox>
  </object>
  <object>
    <name>X</name>
    <occluded>0</occluded>
    <bndbox>
      <xmin>296.4</xmin>
      <ymin>455.48</ymin>
      <xmax>322.56</xmax>
      <ymax>498.0</ymax>
    </bndbox>
  </object>
  <object>
    <name>X</name>
    <occluded>0</occluded>
    <bndbox>
      <xmin>433.82</xmin>
      <ymin>447.46</ymin>
      <xmax>460.68</xmax>
      <ymax>496.29</ymax>
    </bndbox>
  </object>
  <object>
    <name>X</name>
    <occluded>0</occluded>
    <bndbox>
      <xmin>460.68</xmin>
      <ymin>459.32</ymin>
      <xmax>488.58</xmax>
      <ymax>496.99</ymax>
    </bndbox>
  </object>
  <object>
    <name>X</name>
    <occluded>0</occluded>
    <bndbox>
      <xmin>489.28</xmin>
      <ymin>458.97</ymin>
      <xmax>516.83</xmax>
      <ymax>496.29</ymax>
    </bndbox>
  </object>
  <object>
    <name>odometer</name>
    <occluded>0</occluded>
    <bndbox>
      <xmin>150.48</xmin>
      <ymin>431.01</ymin>
      <xmax>611.28</xmax>
      <ymax>637.95</ymax>
    </bndbox>
  </object>
  <object>
    <name>5</name>
    <occluded>0</occluded>
    <bndbox>
      <xmin>318.57</xmin>
      <ymin>559.41</ymin>
      <xmax>349.67</xmax>
      <ymax>610.03</ymax>
    </bndbox>
  </object>
  <object>
    <name>1</name>
    <occluded>0</occluded>
    <bndbox>
      <xmin>305.33</xmin>
      <ymin>561.98</ymin>
      <xmax>316.38</xmax>
      <ymax>610.7</ymax>
    </bndbox>
  </object>
  <object>
    <name>1</name>
    <occluded>0</occluded>
    <bndbox>
      <xmin>384.63</xmin>
      <ymin>560.52</ymin>
      <xmax>395.68</xmax>
      <ymax>608.24</ymax>
    </bndbox>
  </object>
  <object>
    <name>3</name>
    <occluded>0</occluded>
    <bndbox>
      <xmin>399.7</xmin>
      <ymin>558.51</ymin>
      <xmax>429.33</xmax>
      <ymax>609.24</ymax>
    </bndbox>
  </object>
  <object>
    <name>3</name>
    <occluded>0</occluded>
    <bndbox>
      <xmin>415.27</xmin>
      <ymin>502.26</ymin>
      <xmax>440.89</xmax>
      <ymax>545.96</ymax>
    </bndbox>
  </object>
  <object>
    <name>2</name>
    <occluded>0</occluded>
    <bndbox>
      <xmin>378.11</xmin>
      <ymin>448.52</ymin>
      <xmax>406.23</xmax>
      <ymax>497.74</ymax>
    </bndbox>
  </object>
  <object>
    <name>2</name>
    <occluded>0</occluded>
    <bndbox>
      <xmin>264.6</xmin>
      <ymin>505.28</ymin>
      <xmax>291.22</xmax>
      <ymax>547.97</ymax>
    </bndbox>
  </object>
  <object>
    <name>4</name>
    <occluded>0</occluded>
    <bndbox>
      <xmin>293.73</xmin>
      <ymin>506.28</ymin>
      <xmax>323.36</xmax>
      <ymax>544.95</ymax>
    </bndbox>
  </object>
  <object>
    <name>7</name>
    <occluded>0</occluded>
    <bndbox>
      <xmin>357.51</xmin>
      <ymin>502.76</ymin>
      <xmax>384.64</xmax>
      <ymax>545.96</ymax>
    </bndbox>
  </object>
  <object>
    <name>7</name>
    <occluded>0</occluded>
    <bndbox>
      <xmin>385.64</xmin>
      <ymin>502.76</ymin>
      <xmax>411.76</xmax>
      <ymax>543.95</ymax>
    </bndbox>
  </object>
  <object>
    <name>0</name>
    <occluded>0</occluded>
    <bndbox>
      <xmin>324.37</xmin>
      <ymin>503.77</ymin>
      <xmax>352.99</xmax>
      <ymax>547.97</ymax>
    </bndbox>
  </object>
  <object>
    <name>X</name>
    <occluded>0</occluded>
    <bndbox>
      <xmin>352.14</xmin>
      <ymin>566.29</ymin>
      <xmax>365.04</xmax>
      <ymax>602.91</ymax>
    </bndbox>
  </object>
  <object>
    <name>X</name>
    <occluded>0</occluded>
    <bndbox>
      <xmin>443.59</xmin>
      <ymin>503.26</ymin>
      <xmax>456.14</xmax>
      <ymax>526.63</ymax>
    </bndbox>
  </object>
</annotation>
