<annotation>
  <folder></folder>
  <filename>00000404-PHOTO-2020-11-27-13-56-50.jpg</filename>
  <source>
    <database>Unknown</database>
    <annotation>Unknown</annotation>
    <image>Unknown</image>
  </source>
  <size>
    <width>768</width>
    <height>1024</height>
    <depth></depth>
  </size>
  <segmented>0</segmented>
  <object>
    <name>0</name>
    <occluded>0</occluded>
    <bndbox>
      <xmin>345.51</xmin>
      <ymin>551.47</ymin>
      <xmax>355.31</xmax>
      <ymax>567.12</ymax>
    </bndbox>
  </object>
  <object>
    <name>0</name>
    <occluded>0</occluded>
    <bndbox>
      <xmin>382.22</xmin>
      <ymin>515.8</ymin>
      <xmax>391.31</xmax>
      <ymax>531.52</ymax>
    </bndbox>
  </object>
  <object>
    <name>0</name>
    <occluded>0</occluded>
    <bndbox>
      <xmin>399.96</xmin>
      <ymin>516.05</ymin>
      <xmax>408.83</xmax>
      <ymax>531.06</ymax>
    </bndbox>
  </object>
  <object>
    <name>,</name>
    <occluded>0</occluded>
    <bndbox>
      <xmin>391.29</xmin>
      <ymin>525.15</ymin>
      <xmax>396.09</xmax>
      <ymax>531.06</ymax>
    </bndbox>
  </object>
  <object>
    <name>,</name>
    <occluded>0</occluded>
    <bndbox>
      <xmin>329.66</xmin>
      <ymin>526.06</ymin>
      <xmax>333.55</xmax>
      <ymax>531.29</ymax>
    </bndbox>
  </object>
  <object>
    <name>X</name>
    <occluded>0</occluded>
    <bndbox>
      <xmin>326.15</xmin>
      <ymin>555.48</ymin>
      <xmax>333.54</xmax>
      <ymax>567.23</ymax>
    </bndbox>
  </object>
  <object>
    <name>4</name>
    <occluded>0</occluded>
    <bndbox>
      <xmin>315.58</xmin>
      <ymin>555.9</ymin>
      <xmax>323.31</xmax>
      <ymax>566.59</ymax>
    </bndbox>
  </object>
  <object>
    <name>3</name>
    <occluded>0</occluded>
    <bndbox>
      <xmin>339.01</xmin>
      <ymin>533.38</ymin>
      <xmax>347.19</xmax>
      <ymax>546.58</ymax>
    </bndbox>
  </object>
  <object>
    <name>2</name>
    <occluded>0</occluded>
    <bndbox>
      <xmin>370.39</xmin>
      <ymin>551.1</ymin>
      <xmax>381.1</xmax>
      <ymax>567.27</ymax>
    </bndbox>
  </object>
  <object>
    <name>2</name>
    <occluded>0</occluded>
    <bndbox>
      <xmin>328.32</xmin>
      <ymin>533.16</ymin>
      <xmax>337.41</xmax>
      <ymax>547.26</ymax>
    </bndbox>
  </object>
  <object>
    <name>X</name>
    <occluded>0</occluded>
    <bndbox>
      <xmin>416.56</xmin>
      <ymin>519.28</ymin>
      <xmax>426.79</xmax>
      <ymax>531.34</ymax>
    </bndbox>
  </object>
  <object>
    <name>X</name>
    <occluded>0</occluded>
    <bndbox>
      <xmin>409.05</xmin>
      <ymin>516.33</ymin>
      <xmax>416.1</xmax>
      <ymax>531.57</ymax>
    </bndbox>
  </object>
  <object>
    <name>X</name>
    <occluded>0</occluded>
    <bndbox>
      <xmin>320.58</xmin>
      <ymin>519.97</ymin>
      <xmax>329.68</xmax>
      <ymax>530.66</ymax>
    </bndbox>
  </object>
  <object>
    <name>X</name>
    <occluded>0</occluded>
    <bndbox>
      <xmin>303.07</xmin>
      <ymin>515.87</ymin>
      <xmax>312.62</xmax>
      <ymax>531.57</ymax>
    </bndbox>
  </object>
  <object>
    <name>odometer</name>
    <occluded>0</occluded>
    <bndbox>
      <xmin>290.2</xmin>
      <ymin>508.63</ymin>
      <xmax>439.2</xmax>
      <ymax>577.23</ymax>
    </bndbox>
  </object>
  <object>
    <name>0</name>
    <occluded>0</occluded>
    <bndbox>
      <xmin>360.04</xmin>
      <ymin>551.63</ymin>
      <xmax>369.68</xmax>
      <ymax>567.13</ymax>
    </bndbox>
  </object>
  <object>
    <name>9</name>
    <occluded>0</occluded>
    <bndbox>
      <xmin>375.84</xmin>
      <ymin>533.01</ymin>
      <xmax>384.68</xmax>
      <ymax>547.38</ymax>
    </bndbox>
  </object>
  <object>
    <name>5</name>
    <occluded>0</occluded>
    <bndbox>
      <xmin>366.68</xmin>
      <ymin>533.17</ymin>
      <xmax>375.36</xmax>
      <ymax>547.23</ymax>
    </bndbox>
  </object>
  <object>
    <name>7</name>
    <occluded>0</occluded>
    <bndbox>
      <xmin>358.31</xmin>
      <ymin>533.2</ymin>
      <xmax>366.05</xmax>
      <ymax>546.28</ymax>
    </bndbox>
  </object>
  <object>
    <name>1</name>
    <occluded>0</occluded>
    <bndbox>
      <xmin>352.94</xmin>
      <ymin>534.1</ymin>
      <xmax>356.89</xmax>
      <ymax>546.91</ymax>
    </bndbox>
  </object>
  <object>
    <name>1</name>
    <occluded>0</occluded>
    <bndbox>
      <xmin>340.93</xmin>
      <ymin>551.79</ymin>
      <xmax>345.2</xmax>
      <ymax>567.28</ymax>
    </bndbox>
  </object>
  <object>
    <name>X</name>
    <occluded>0</occluded>
    <bndbox>
      <xmin>356.49</xmin>
      <ymin>554.36</ymin>
      <xmax>359.41</xmax>
      <ymax>564.41</ymax>
    </bndbox>
  </object>
</annotation>
