<annotation>
  <folder></folder>
  <filename>00000347-PHOTO-2020-11-26-00-45-22.jpg</filename>
  <source>
    <database>Unknown</database>
    <annotation>Unknown</annotation>
    <image>Unknown</image>
  </source>
  <size>
    <width>505</width>
    <height>1024</height>
    <depth></depth>
  </size>
  <segmented>0</segmented>
  <object>
    <name>1</name>
    <occluded>0</occluded>
    <bndbox>
      <xmin>254.64</xmin>
      <ymin>527.37</ymin>
      <xmax>259.06</xmax>
      <ymax>543.18</ymax>
    </bndbox>
  </object>
  <object>
    <name>5</name>
    <occluded>0</occluded>
    <bndbox>
      <xmin>293.19</xmin>
      <ymin>504.1</ymin>
      <xmax>306.08</xmax>
      <ymax>524.7</ymax>
    </bndbox>
  </object>
  <object>
    <name>4</name>
    <occluded>0</occluded>
    <bndbox>
      <xmin>298.31</xmin>
      <ymin>527.4</ymin>
      <xmax>307.97</xmax>
      <ymax>541.61</ymax>
    </bndbox>
  </object>
  <object>
    <name>2</name>
    <occluded>0</occluded>
    <bndbox>
      <xmin>236.52</xmin>
      <ymin>526.64</ymin>
      <xmax>245.8</xmax>
      <ymax>542.0</ymax>
    </bndbox>
  </object>
  <object>
    <name>7</name>
    <occluded>0</occluded>
    <bndbox>
      <xmin>262.87</xmin>
      <ymin>526.26</ymin>
      <xmax>271.01</xmax>
      <ymax>541.04</ymax>
    </bndbox>
  </object>
  <object>
    <name>5</name>
    <occluded>0</occluded>
    <bndbox>
      <xmin>274.05</xmin>
      <ymin>526.64</ymin>
      <xmax>282.2</xmax>
      <ymax>541.61</ymax>
    </bndbox>
  </object>
  <object>
    <name>9</name>
    <occluded>0</occluded>
    <bndbox>
      <xmin>285.99</xmin>
      <ymin>526.64</ymin>
      <xmax>295.65</xmax>
      <ymax>541.61</ymax>
    </bndbox>
  </object>
  <object>
    <name>8</name>
    <occluded>0</occluded>
    <bndbox>
      <xmin>273.91</xmin>
      <ymin>504.0</ymin>
      <xmax>287.65</xmax>
      <ymax>525.02</ymax>
    </bndbox>
  </object>
  <object>
    <name>0</name>
    <occluded>0</occluded>
    <bndbox>
      <xmin>254.48</xmin>
      <ymin>504.16</ymin>
      <xmax>269.33</xmax>
      <ymax>524.86</ymax>
    </bndbox>
  </object>
  <object>
    <name>odometer</name>
    <occluded>0</occluded>
    <bndbox>
      <xmin>226.3</xmin>
      <ymin>498.31</ymin>
      <xmax>318.91</xmax>
      <ymax>545.44</ymax>
    </bndbox>
  </object>
  <object>
    <name>1</name>
    <occluded>0</occluded>
    <bndbox>
      <xmin>244.53</xmin>
      <ymin>505.26</ymin>
      <xmax>250.53</xmax>
      <ymax>523.91</ymax>
    </bndbox>
  </object>
</annotation>
