<annotation>
  <folder></folder>
  <filename>00001353-PHOTO-2020-12-12-10-58-41.jpg</filename>
  <source>
    <database>Unknown</database>
    <annotation>Unknown</annotation>
    <image>Unknown</image>
  </source>
  <size>
    <width>576</width>
    <height>1024</height>
    <depth></depth>
  </size>
  <segmented>0</segmented>
  <object>
    <name>X</name>
    <occluded>0</occluded>
    <bndbox>
      <xmin>188.49</xmin>
      <ymin>393.79</ymin>
      <xmax>218.22</xmax>
      <ymax>453.26</ymax>
    </bndbox>
  </object>
  <object>
    <name>X</name>
    <occluded>0</occluded>
    <bndbox>
      <xmin>217.79</xmin>
      <ymin>390.29</ymin>
      <xmax>250.58</xmax>
      <ymax>449.76</ymax>
    </bndbox>
  </object>
  <object>
    <name>6</name>
    <occluded>0</occluded>
    <bndbox>
      <xmin>257.48</xmin>
      <ymin>455.2</ymin>
      <xmax>289.85</xmax>
      <ymax>506.74</ymax>
    </bndbox>
  </object>
  <object>
    <name>6</name>
    <occluded>0</occluded>
    <bndbox>
      <xmin>290.28</xmin>
      <ymin>453.07</ymin>
      <xmax>325.2</xmax>
      <ymax>505.89</ymax>
    </bndbox>
  </object>
  <object>
    <name>7</name>
    <occluded>0</occluded>
    <bndbox>
      <xmin>312.92</xmin>
      <ymin>516.8</ymin>
      <xmax>349.11</xmax>
      <ymax>575.07</ymax>
    </bndbox>
  </object>
  <object>
    <name>7</name>
    <occluded>0</occluded>
    <bndbox>
      <xmin>326.41</xmin>
      <ymin>450.55</ymin>
      <xmax>357.69</xmax>
      <ymax>502.69</ymax>
    </bndbox>
  </object>
  <object>
    <name>3</name>
    <occluded>0</occluded>
    <bndbox>
      <xmin>272.3</xmin>
      <ymin>517.99</ymin>
      <xmax>309.74</xmax>
      <ymax>580.6</ymax>
    </bndbox>
  </object>
  <object>
    <name>1</name>
    <occluded>0</occluded>
    <bndbox>
      <xmin>175.34</xmin>
      <ymin>459.3</ymin>
      <xmax>188.48</xmax>
      <ymax>508.29</ymax>
    </bndbox>
  </object>
  <object>
    <name>1</name>
    <occluded>0</occluded>
    <bndbox>
      <xmin>204.73</xmin>
      <ymin>523.02</ymin>
      <xmax>218.58</xmax>
      <ymax>579.46</ymax>
    </bndbox>
  </object>
  <object>
    <name>4</name>
    <occluded>0</occluded>
    <bndbox>
      <xmin>469.9</xmin>
      <ymin>381.98</ymin>
      <xmax>509.76</xmax>
      <ymax>440.76</ymax>
    </bndbox>
  </object>
  <object>
    <name>9</name>
    <occluded>0</occluded>
    <bndbox>
      <xmin>373.76</xmin>
      <ymin>384.05</ymin>
      <xmax>407.84</xmax>
      <ymax>446.2</ymax>
    </bndbox>
  </object>
  <object>
    <name>X</name>
    <occluded>0</occluded>
    <bndbox>
      <xmin>358.42</xmin>
      <ymin>451.56</ymin>
      <xmax>373.28</xmax>
      <ymax>481.73</ymax>
    </bndbox>
  </object>
  <object>
    <name>X</name>
    <occluded>0</occluded>
    <bndbox>
      <xmin>250.58</xmin>
      <ymin>390.29</ymin>
      <xmax>283.82</xmax>
      <ymax>448.45</ymax>
    </bndbox>
  </object>
  <object>
    <name>3</name>
    <occluded>0</occluded>
    <bndbox>
      <xmin>224.68</xmin>
      <ymin>455.46</ymin>
      <xmax>257.05</xmax>
      <ymax>508.27</ymax>
    </bndbox>
  </object>
  <object>
    <name>3</name>
    <occluded>0</occluded>
    <bndbox>
      <xmin>407.48</xmin>
      <ymin>382.63</ymin>
      <xmax>442.62</xmax>
      <ymax>442.27</ymax>
    </bndbox>
  </object>
  <object>
    <name>,</name>
    <occluded>0</occluded>
    <bndbox>
      <xmin>442.27</xmin>
      <ymin>417.42</ymin>
      <xmax>461.79</xmax>
      <ymax>441.56</ymax>
    </bndbox>
  </object>
  <object>
    <name>8</name>
    <occluded>0</occluded>
    <bndbox>
      <xmin>220.98</xmin>
      <ymin>521.01</ymin>
      <xmax>258.29</xmax>
      <ymax>579.79</ymax>
    </bndbox>
  </object>
  <object>
    <name>odometer</name>
    <occluded>0</occluded>
    <bndbox>
      <xmin>24.8</xmin>
      <ymin>363.5</ymin>
      <xmax>538.3</xmax>
      <ymax>606.6</ymax>
    </bndbox>
  </object>
  <object>
    <name>6</name>
    <occluded>0</occluded>
    <bndbox>
      <xmin>189.11</xmin>
      <ymin>457.03</ymin>
      <xmax>224.04</xmax>
      <ymax>509.0</ymax>
    </bndbox>
  </object>
  <object>
    <name>X</name>
    <occluded>0</occluded>
    <bndbox>
      <xmin>373.02</xmin>
      <ymin>455.27</ymin>
      <xmax>400.57</xmax>
      <ymax>480.2</ymax>
    </bndbox>
  </object>
  <object>
    <name>X</name>
    <occluded>0</occluded>
    <bndbox>
      <xmin>59.49</xmin>
      <ymin>396.42</ymin>
      <xmax>91.41</xmax>
      <ymax>459.38</ymax>
    </bndbox>
  </object>
  <object>
    <name>X</name>
    <occluded>0</occluded>
    <bndbox>
      <xmin>94.91</xmin>
      <ymin>397.73</ymin>
      <xmax>125.96</xmax>
      <ymax>457.2</ymax>
    </bndbox>
  </object>
  <object>
    <name>X</name>
    <occluded>0</occluded>
    <bndbox>
      <xmin>126.39</xmin>
      <ymin>395.1</ymin>
      <xmax>155.26</xmax>
      <ymax>454.14</ymax>
    </bndbox>
  </object>
  <object>
    <name>X</name>
    <occluded>0</occluded>
    <bndbox>
      <xmin>156.57</xmin>
      <ymin>395.1</ymin>
      <xmax>186.74</xmax>
      <ymax>451.95</ymax>
    </bndbox>
  </object>
</annotation>
