<annotation>
  <folder></folder>
  <filename>00001007-PHOTO-2020-12-18-20-15-49.jpg</filename>
  <source>
    <database>Unknown</database>
    <annotation>Unknown</annotation>
    <image>Unknown</image>
  </source>
  <size>
    <width>550</width>
    <height>1600</height>
    <depth></depth>
  </size>
  <segmented>0</segmented>
  <object>
    <name>X</name>
    <occluded>0</occluded>
    <bndbox>
      <xmin>253.6</xmin>
      <ymin>613.36</ymin>
      <xmax>271.17</xmax>
      <ymax>639.51</ymax>
    </bndbox>
  </object>
  <object>
    <name>2</name>
    <occluded>0</occluded>
    <bndbox>
      <xmin>263.1</xmin>
      <ymin>677.66</ymin>
      <xmax>284.04</xmax>
      <ymax>712.81</ymax>
    </bndbox>
  </object>
  <object>
    <name>0</name>
    <occluded>0</occluded>
    <bndbox>
      <xmin>284.0</xmin>
      <ymin>678.09</ymin>
      <xmax>307.61</xmax>
      <ymax>711.96</ymax>
    </bndbox>
  </object>
  <object>
    <name>1</name>
    <occluded>0</occluded>
    <bndbox>
      <xmin>323.05</xmin>
      <ymin>678.52</ymin>
      <xmax>334.62</xmax>
      <ymax>710.24</ymax>
    </bndbox>
  </object>
  <object>
    <name>1</name>
    <occluded>0</occluded>
    <bndbox>
      <xmin>317.9</xmin>
      <ymin>643.37</ymin>
      <xmax>326.48</xmax>
      <ymax>672.52</ymax>
    </bndbox>
  </object>
  <object>
    <name>1</name>
    <occluded>0</occluded>
    <bndbox>
      <xmin>279.32</xmin>
      <ymin>643.37</ymin>
      <xmax>289.18</xmax>
      <ymax>671.23</ymax>
    </bndbox>
  </object>
  <object>
    <name>1</name>
    <occluded>0</occluded>
    <bndbox>
      <xmin>260.46</xmin>
      <ymin>642.94</ymin>
      <xmax>272.46</xmax>
      <ymax>670.8</ymax>
    </bndbox>
  </object>
  <object>
    <name>1</name>
    <occluded>0</occluded>
    <bndbox>
      <xmin>205.58</xmin>
      <ymin>640.79</ymin>
      <xmax>215.87</xmax>
      <ymax>669.09</ymax>
    </bndbox>
  </object>
  <object>
    <name>1</name>
    <occluded>0</occluded>
    <bndbox>
      <xmin>307.18</xmin>
      <ymin>606.93</ymin>
      <xmax>323.05</xmax>
      <ymax>640.79</ymax>
    </bndbox>
  </object>
  <object>
    <name>X</name>
    <occluded>0</occluded>
    <bndbox>
      <xmin>373.2</xmin>
      <ymin>647.22</ymin>
      <xmax>387.78</xmax>
      <ymax>659.66</ymax>
    </bndbox>
  </object>
  <object>
    <name>X</name>
    <occluded>0</occluded>
    <bndbox>
      <xmin>364.4</xmin>
      <ymin>643.79</ymin>
      <xmax>373.1</xmax>
      <ymax>660.09</ymax>
    </bndbox>
  </object>
  <object>
    <name>X</name>
    <occluded>0</occluded>
    <bndbox>
      <xmin>395.2</xmin>
      <ymin>615.93</ymin>
      <xmax>414.2</xmax>
      <ymax>641.65</ymax>
    </bndbox>
  </object>
  <object>
    <name>X</name>
    <occluded>0</occluded>
    <bndbox>
      <xmin>377.56</xmin>
      <ymin>615.5</ymin>
      <xmax>394.9</xmax>
      <ymax>641.65</ymax>
    </bndbox>
  </object>
  <object>
    <name>X</name>
    <occluded>0</occluded>
    <bndbox>
      <xmin>358.2</xmin>
      <ymin>608.21</ymin>
      <xmax>377.49</xmax>
      <ymax>640.79</ymax>
    </bndbox>
  </object>
  <object>
    <name>X</name>
    <occluded>0</occluded>
    <bndbox>
      <xmin>271.17</xmin>
      <ymin>614.21</ymin>
      <xmax>290.47</xmax>
      <ymax>640.79</ymax>
    </bndbox>
  </object>
  <object>
    <name>X</name>
    <occluded>0</occluded>
    <bndbox>
      <xmin>234.31</xmin>
      <ymin>605.21</ymin>
      <xmax>253.6</xmax>
      <ymax>639.51</ymax>
    </bndbox>
  </object>
  <object>
    <name>odometer</name>
    <occluded>0</occluded>
    <bndbox>
      <xmin>174.14</xmin>
      <ymin>603.29</ymin>
      <xmax>468.5</xmax>
      <ymax>739.43</ymax>
    </bndbox>
  </object>
  <object>
    <name>1</name>
    <occluded>0</occluded>
    <bndbox>
      <xmin>354.34</xmin>
      <ymin>645.94</ymin>
      <xmax>364.2</xmax>
      <ymax>672.52</ymax>
    </bndbox>
  </object>
  <object>
    <name>4</name>
    <occluded>0</occluded>
    <bndbox>
      <xmin>335.05</xmin>
      <ymin>679.38</ymin>
      <xmax>357.77</xmax>
      <ymax>710.67</ymax>
    </bndbox>
  </object>
  <object>
    <name>5</name>
    <occluded>0</occluded>
    <bndbox>
      <xmin>327.3</xmin>
      <ymin>642.94</ymin>
      <xmax>346.2</xmax>
      <ymax>672.95</ymax>
    </bndbox>
  </object>
  <object>
    <name>8</name>
    <occluded>0</occluded>
    <bndbox>
      <xmin>290.04</xmin>
      <ymin>642.08</ymin>
      <xmax>309.33</xmax>
      <ymax>671.66</ymax>
    </bndbox>
  </object>
  <object>
    <name>8</name>
    <occluded>0</occluded>
    <bndbox>
      <xmin>323.9</xmin>
      <ymin>606.93</ymin>
      <xmax>344.05</xmax>
      <ymax>640.36</ymax>
    </bndbox>
  </object>
</annotation>
