<annotation>
  <folder></folder>
  <filename>00001384-PHOTO-2020-12-12-11-00-04.jpg</filename>
  <source>
    <database>Unknown</database>
    <annotation>Unknown</annotation>
    <image>Unknown</image>
  </source>
  <size>
    <width>576</width>
    <height>1024</height>
    <depth></depth>
  </size>
  <segmented>0</segmented>
  <object>
    <name>9</name>
    <occluded>0</occluded>
    <bndbox>
      <xmin>256.33</xmin>
      <ymin>537.61</ymin>
      <xmax>269.4</xmax>
      <ymax>557.21</ymax>
    </bndbox>
  </object>
  <object>
    <name>1</name>
    <occluded>0</occluded>
    <bndbox>
      <xmin>286.39</xmin>
      <ymin>511.04</ymin>
      <xmax>292.48</xmax>
      <ymax>527.6</ymax>
    </bndbox>
  </object>
  <object>
    <name>1</name>
    <occluded>0</occluded>
    <bndbox>
      <xmin>234.34</xmin>
      <ymin>534.78</ymin>
      <xmax>241.74</xmax>
      <ymax>555.04</ymax>
    </bndbox>
  </object>
  <object>
    <name>1</name>
    <occluded>0</occluded>
    <bndbox>
      <xmin>248.3</xmin>
      <ymin>537.18</ymin>
      <xmax>255.24</xmax>
      <ymax>555.69</ymax>
    </bndbox>
  </object>
  <object>
    <name>2</name>
    <occluded>0</occluded>
    <bndbox>
      <xmin>268.5</xmin>
      <ymin>510.61</ymin>
      <xmax>280.72</xmax>
      <ymax>528.47</ymax>
    </bndbox>
  </object>
  <object>
    <name>2</name>
    <occluded>0</occluded>
    <bndbox>
      <xmin>293.79</xmin>
      <ymin>511.9</ymin>
      <xmax>305.55</xmax>
      <ymax>529.3</ymax>
    </bndbox>
  </object>
  <object>
    <name>2</name>
    <occluded>0</occluded>
    <bndbox>
      <xmin>298.8</xmin>
      <ymin>538.7</ymin>
      <xmax>312.08</xmax>
      <ymax>559.83</ymax>
    </bndbox>
  </object>
  <object>
    <name>X</name>
    <occluded>0</occluded>
    <bndbox>
      <xmin>251.76</xmin>
      <ymin>526.29</ymin>
      <xmax>256.99</xmax>
      <ymax>536.31</ymax>
    </bndbox>
  </object>
  <object>
    <name>X</name>
    <occluded>0</occluded>
    <bndbox>
      <xmin>256.77</xmin>
      <ymin>528.69</ymin>
      <xmax>264.83</xmax>
      <ymax>536.96</ymax>
    </bndbox>
  </object>
  <object>
    <name>5</name>
    <occluded>0</occluded>
    <bndbox>
      <xmin>284.21</xmin>
      <ymin>538.7</ymin>
      <xmax>297.27</xmax>
      <ymax>558.3</ymax>
    </bndbox>
  </object>
  <object>
    <name>odometer</name>
    <occluded>0</occluded>
    <bndbox>
      <xmin>220.65</xmin>
      <ymin>505.45</ymin>
      <xmax>318.92</xmax>
      <ymax>566.5</ymax>
    </bndbox>
  </object>
  <object>
    <name>0</name>
    <occluded>0</occluded>
    <bndbox>
      <xmin>269.83</xmin>
      <ymin>537.61</ymin>
      <xmax>282.9</xmax>
      <ymax>557.9</ymax>
    </bndbox>
  </object>
  <object>
    <name>,</name>
    <occluded>0</occluded>
    <bndbox>
      <xmin>290.31</xmin>
      <ymin>525.2</ymin>
      <xmax>293.79</xmax>
      <ymax>530.43</ymax>
    </bndbox>
  </object>
  <object>
    <name>1</name>
    <occluded>0</occluded>
    <bndbox>
      <xmin>262.0</xmin>
      <ymin>510.17</ymin>
      <xmax>268.09</xmax>
      <ymax>526.7</ymax>
    </bndbox>
  </object>
</annotation>
