<annotation>
  <folder></folder>
  <filename>00001274-PHOTO-2020-12-10-20-01-32.jpg</filename>
  <source>
    <database>Unknown</database>
    <annotation>Unknown</annotation>
    <image>Unknown</image>
  </source>
  <size>
    <width>768</width>
    <height>1024</height>
    <depth></depth>
  </size>
  <segmented>0</segmented>
  <object>
    <name>odometer</name>
    <occluded>0</occluded>
    <bndbox>
      <xmin>244.7</xmin>
      <ymin>497.6</ymin>
      <xmax>600.3</xmax>
      <ymax>654.9</ymax>
    </bndbox>
  </object>
  <object>
    <name>X</name>
    <occluded>0</occluded>
    <bndbox>
      <xmin>337.31</xmin>
      <ymin>523.31</ymin>
      <xmax>358.34</xmax>
      <ymax>555.39</ymax>
    </bndbox>
  </object>
  <object>
    <name>8</name>
    <occluded>0</occluded>
    <bndbox>
      <xmin>435.53</xmin>
      <ymin>599.22</ymin>
      <xmax>462.64</xmax>
      <ymax>641.11</ymax>
    </bndbox>
  </object>
  <object>
    <name>6</name>
    <occluded>0</occluded>
    <bndbox>
      <xmin>377.27</xmin>
      <ymin>600.46</ymin>
      <xmax>400.45</xmax>
      <ymax>640.75</ymax>
    </bndbox>
  </object>
  <object>
    <name>6</name>
    <occluded>0</occluded>
    <bndbox>
      <xmin>403.16</xmin>
      <ymin>556.96</ymin>
      <xmax>424.55</xmax>
      <ymax>591.9</ymax>
    </bndbox>
  </object>
  <object>
    <name>1</name>
    <occluded>0</occluded>
    <bndbox>
      <xmin>445.94</xmin>
      <ymin>512.4</ymin>
      <xmax>462.34</xmax>
      <ymax>554.47</ymax>
    </bndbox>
  </object>
  <object>
    <name>X</name>
    <occluded>0</occluded>
    <bndbox>
      <xmin>379.38</xmin>
      <ymin>510.47</ymin>
      <xmax>398.27</xmax>
      <ymax>554.68</ymax>
    </bndbox>
  </object>
  <object>
    <name>1</name>
    <occluded>0</occluded>
    <bndbox>
      <xmin>365.72</xmin>
      <ymin>602.24</ymin>
      <xmax>374.28</xmax>
      <ymax>642.17</ymax>
    </bndbox>
  </object>
  <object>
    <name>1</name>
    <occluded>0</occluded>
    <bndbox>
      <xmin>394.24</xmin>
      <ymin>558.39</ymin>
      <xmax>402.09</xmax>
      <ymax>591.19</ymax>
    </bndbox>
  </object>
  <object>
    <name>4</name>
    <occluded>0</occluded>
    <bndbox>
      <xmin>465.05</xmin>
      <ymin>512.11</ymin>
      <xmax>487.72</xmax>
      <ymax>554.47</ymax>
    </bndbox>
  </object>
  <object>
    <name>4</name>
    <occluded>0</occluded>
    <bndbox>
      <xmin>357.06</xmin>
      <ymin>558.27</ymin>
      <xmax>380.17</xmax>
      <ymax>591.22</ymax>
    </bndbox>
  </object>
  <object>
    <name>4</name>
    <occluded>0</occluded>
    <bndbox>
      <xmin>425.95</xmin>
      <ymin>556.56</ymin>
      <xmax>449.05</xmax>
      <ymax>590.79</ymax>
    </bndbox>
  </object>
  <object>
    <name>3</name>
    <occluded>0</occluded>
    <bndbox>
      <xmin>267.65</xmin>
      <ymin>556.13</ymin>
      <xmax>289.04</xmax>
      <ymax>591.64</ymax>
    </bndbox>
  </object>
  <object>
    <name>9</name>
    <occluded>0</occluded>
    <bndbox>
      <xmin>450.33</xmin>
      <ymin>555.71</ymin>
      <xmax>472.15</xmax>
      <ymax>592.93</ymax>
    </bndbox>
  </object>
  <object>
    <name>3</name>
    <occluded>0</occluded>
    <bndbox>
      <xmin>412.68</xmin>
      <ymin>599.35</ymin>
      <xmax>435.79</xmax>
      <ymax>640.85</ymax>
    </bndbox>
  </object>
  <object>
    <name>2</name>
    <occluded>0</occluded>
    <bndbox>
      <xmin>334.5</xmin>
      <ymin>557.32</ymin>
      <xmax>356.24</xmax>
      <ymax>592.97</ymax>
    </bndbox>
  </object>
  <object>
    <name>X</name>
    <occluded>0</occluded>
    <bndbox>
      <xmin>402.19</xmin>
      <ymin>605.66</ymin>
      <xmax>410.04</xmax>
      <ymax>635.61</ymax>
    </bndbox>
  </object>
  <object>
    <name>X</name>
    <occluded>0</occluded>
    <bndbox>
      <xmin>473.14</xmin>
      <ymin>556.11</ymin>
      <xmax>483.12</xmax>
      <ymax>578.21</ymax>
    </bndbox>
  </object>
  <object>
    <name>X</name>
    <occluded>0</occluded>
    <bndbox>
      <xmin>483.48</xmin>
      <ymin>558.96</ymin>
      <xmax>501.31</xmax>
      <ymax>578.57</ymax>
    </bndbox>
  </object>
  <object>
    <name>X</name>
    <occluded>0</occluded>
    <bndbox>
      <xmin>528.76</xmin>
      <ymin>511.54</ymin>
      <xmax>548.73</xmax>
      <ymax>554.32</ymax>
    </bndbox>
  </object>
  <object>
    <name>X</name>
    <occluded>0</occluded>
    <bndbox>
      <xmin>551.22</xmin>
      <ymin>519.74</ymin>
      <xmax>573.68</xmax>
      <ymax>555.39</ymax>
    </bndbox>
  </object>
  <object>
    <name>X</name>
    <occluded>0</occluded>
    <bndbox>
      <xmin>269.92</xmin>
      <ymin>512.97</ymin>
      <xmax>292.38</xmax>
      <ymax>554.32</ymax>
    </bndbox>
  </object>
  <object>
    <name>X</name>
    <occluded>0</occluded>
    <bndbox>
      <xmin>292.74</xmin>
      <ymin>522.59</ymin>
      <xmax>313.06</xmax>
      <ymax>553.97</ymax>
    </bndbox>
  </object>
  <object>
    <name>X</name>
    <occluded>0</occluded>
    <bndbox>
      <xmin>313.42</xmin>
      <ymin>523.66</ymin>
      <xmax>336.24</xmax>
      <ymax>554.68</ymax>
    </bndbox>
  </object>
  <object>
    <name>X</name>
    <occluded>0</occluded>
    <bndbox>
      <xmin>360.12</xmin>
      <ymin>512.61</ymin>
      <xmax>375.1</xmax>
      <ymax>553.97</ymax>
    </bndbox>
  </object>
</annotation>
