<annotation>
  <folder></folder>
  <filename>00001321-PHOTO-2020-12-11-13-27-55.jpg</filename>
  <source>
    <database>Unknown</database>
    <annotation>Unknown</annotation>
    <image>Unknown</image>
  </source>
  <size>
    <width>576</width>
    <height>1024</height>
    <depth></depth>
  </size>
  <segmented>0</segmented>
  <object>
    <name>1</name>
    <occluded>0</occluded>
    <bndbox>
      <xmin>204.0</xmin>
      <ymin>502.42</ymin>
      <xmax>210.91</xmax>
      <ymax>518.52</ymax>
    </bndbox>
  </object>
  <object>
    <name>6</name>
    <occluded>0</occluded>
    <bndbox>
      <xmin>230.76</xmin>
      <ymin>495.76</ymin>
      <xmax>242.89</xmax>
      <ymax>513.34</ymax>
    </bndbox>
  </object>
  <object>
    <name>1</name>
    <occluded>0</occluded>
    <bndbox>
      <xmin>246.26</xmin>
      <ymin>492.79</ymin>
      <xmax>252.95</xmax>
      <ymax>510.37</ymax>
    </bndbox>
  </object>
  <object>
    <name>6</name>
    <occluded>0</occluded>
    <bndbox>
      <xmin>208.79</xmin>
      <ymin>499.95</ymin>
      <xmax>220.93</xmax>
      <ymax>517.31</ymax>
    </bndbox>
  </object>
  <object>
    <name>4</name>
    <occluded>0</occluded>
    <bndbox>
      <xmin>237.66</xmin>
      <ymin>515.43</ymin>
      <xmax>252.1</xmax>
      <ymax>532.16</ymax>
    </bndbox>
  </object>
  <object>
    <name>odometer</name>
    <occluded>0</occluded>
    <bndbox>
      <xmin>149.32</xmin>
      <ymin>451.71</ymin>
      <xmax>328.65</xmax>
      <ymax>559.57</ymax>
    </bndbox>
  </object>
  <object>
    <name>8</name>
    <occluded>0</occluded>
    <bndbox>
      <xmin>250.21</xmin>
      <ymin>511.87</ymin>
      <xmax>264.65</xmax>
      <ymax>531.75</ymax>
    </bndbox>
  </object>
  <object>
    <name>0</name>
    <occluded>0</occluded>
    <bndbox>
      <xmin>222.39</xmin>
      <ymin>519.4</ymin>
      <xmax>235.57</xmax>
      <ymax>538.02</ymax>
    </bndbox>
  </object>
  <object>
    <name>1</name>
    <occluded>0</occluded>
    <bndbox>
      <xmin>216.97</xmin>
      <ymin>521.24</ymin>
      <xmax>223.88</xmax>
      <ymax>538.82</ymax>
    </bndbox>
  </object>
  <object>
    <name>3</name>
    <occluded>0</occluded>
    <bndbox>
      <xmin>219.48</xmin>
      <ymin>497.81</ymin>
      <xmax>232.04</xmax>
      <ymax>514.97</ymax>
    </bndbox>
  </object>
  <object>
    <name>3</name>
    <occluded>0</occluded>
    <bndbox>
      <xmin>252.18</xmin>
      <ymin>491.08</ymin>
      <xmax>263.48</xmax>
      <ymax>508.23</ymax>
    </bndbox>
  </object>
</annotation>
