<annotation>
  <folder></folder>
  <filename>00000683-PHOTO-2020-12-02-17-31-21.jpg</filename>
  <source>
    <database>Unknown</database>
    <annotation>Unknown</annotation>
    <image>Unknown</image>
  </source>
  <size>
    <width>1024</width>
    <height>768</height>
    <depth></depth>
  </size>
  <segmented>0</segmented>
  <object>
    <name>X</name>
    <occluded>0</occluded>
    <bndbox>
      <xmin>660.71</xmin>
      <ymin>531.55</ymin>
      <xmax>667.59</xmax>
      <ymax>543.99</ymax>
    </bndbox>
  </object>
  <object>
    <name>X</name>
    <occluded>0</occluded>
    <bndbox>
      <xmin>589.0</xmin>
      <ymin>502.75</ymin>
      <xmax>604.18</xmax>
      <ymax>525.95</ymax>
    </bndbox>
  </object>
  <object>
    <name>X</name>
    <occluded>0</occluded>
    <bndbox>
      <xmin>575.08</xmin>
      <ymin>505.07</ymin>
      <xmax>588.16</xmax>
      <ymax>524.47</ymax>
    </bndbox>
  </object>
  <object>
    <name>X</name>
    <occluded>0</occluded>
    <bndbox>
      <xmin>561.17</xmin>
      <ymin>497.9</ymin>
      <xmax>574.66</xmax>
      <ymax>524.68</ymax>
    </bndbox>
  </object>
  <object>
    <name>X</name>
    <occluded>0</occluded>
    <bndbox>
      <xmin>685.16</xmin>
      <ymin>510.34</ymin>
      <xmax>698.87</xmax>
      <ymax>530.17</ymax>
    </bndbox>
  </object>
  <object>
    <name>X</name>
    <occluded>0</occluded>
    <bndbox>
      <xmin>670.82</xmin>
      <ymin>510.76</ymin>
      <xmax>684.53</xmax>
      <ymax>529.11</ymax>
    </bndbox>
  </object>
  <object>
    <name>X</name>
    <occluded>0</occluded>
    <bndbox>
      <xmin>656.9</xmin>
      <ymin>503.17</ymin>
      <xmax>670.19</xmax>
      <ymax>528.48</ymax>
    </bndbox>
  </object>
  <object>
    <name>X</name>
    <occluded>0</occluded>
    <bndbox>
      <xmin>614.73</xmin>
      <ymin>561.59</ymin>
      <xmax>620.63</xmax>
      <ymax>582.25</ymax>
    </bndbox>
  </object>
  <object>
    <name>4</name>
    <occluded>0</occluded>
    <bndbox>
      <xmin>632.44</xmin>
      <ymin>529.74</ymin>
      <xmax>646.36</xmax>
      <ymax>552.94</ymax>
    </bndbox>
  </object>
  <object>
    <name>X</name>
    <occluded>0</occluded>
    <bndbox>
      <xmin>667.46</xmin>
      <ymin>534.28</ymin>
      <xmax>679.91</xmax>
      <ymax>544.54</ymax>
    </bndbox>
  </object>
  <object>
    <name>9</name>
    <occluded>0</occluded>
    <bndbox>
      <xmin>637.71</xmin>
      <ymin>558.85</ymin>
      <xmax>653.74</xmax>
      <ymax>586.05</ymax>
    </bndbox>
  </object>
  <object>
    <name>0</name>
    <occluded>0</occluded>
    <bndbox>
      <xmin>602.92</xmin>
      <ymin>528.69</ymin>
      <xmax>616.2</xmax>
      <ymax>552.1</ymax>
    </bndbox>
  </object>
  <object>
    <name>0</name>
    <occluded>0</occluded>
    <bndbox>
      <xmin>598.91</xmin>
      <ymin>557.37</ymin>
      <xmax>613.67</xmax>
      <ymax>584.57</ymax>
    </bndbox>
  </object>
  <object>
    <name>3</name>
    <occluded>0</occluded>
    <bndbox>
      <xmin>647.42</xmin>
      <ymin>530.8</ymin>
      <xmax>659.86</xmax>
      <ymax>554.84</ymax>
    </bndbox>
  </object>
  <object>
    <name>3</name>
    <occluded>0</occluded>
    <bndbox>
      <xmin>622.32</xmin>
      <ymin>558.85</ymin>
      <xmax>636.24</xmax>
      <ymax>585.21</ymax>
    </bndbox>
  </object>
  <object>
    <name>2</name>
    <occluded>0</occluded>
    <bndbox>
      <xmin>628.65</xmin>
      <ymin>500.64</ymin>
      <xmax>644.88</xmax>
      <ymax>528.06</ymax>
    </bndbox>
  </object>
  <object>
    <name>1</name>
    <occluded>0</occluded>
    <bndbox>
      <xmin>591.53</xmin>
      <ymin>558.0</ymin>
      <xmax>597.65</xmax>
      <ymax>587.53</ymax>
    </bndbox>
  </object>
  <object>
    <name>1</name>
    <occluded>0</occluded>
    <bndbox>
      <xmin>624.85</xmin>
      <ymin>528.9</ymin>
      <xmax>632.02</xmax>
      <ymax>552.94</ymax>
    </bndbox>
  </object>
  <object>
    <name>1</name>
    <occluded>0</occluded>
    <bndbox>
      <xmin>579.85</xmin>
      <ymin>527.55</ymin>
      <xmax>587.65</xmax>
      <ymax>551.59</ymax>
    </bndbox>
  </object>
  <object>
    <name>9</name>
    <occluded>0</occluded>
    <bndbox>
      <xmin>587.74</xmin>
      <ymin>527.85</ymin>
      <xmax>601.65</xmax>
      <ymax>551.25</ymax>
    </bndbox>
  </object>
  <object>
    <name>odometer</name>
    <occluded>0</occluded>
    <bndbox>
      <xmin>513.58</xmin>
      <ymin>486.57</ymin>
      <xmax>748.92</xmax>
      <ymax>601.54</ymax>
    </bndbox>
  </object>
</annotation>
