<annotation>
  <folder></folder>
  <filename>00000679-PHOTO-2020-12-02-17-31-21.jpg</filename>
  <source>
    <database>Unknown</database>
    <annotation>Unknown</annotation>
    <image>Unknown</image>
  </source>
  <size>
    <width>576</width>
    <height>1024</height>
    <depth></depth>
  </size>
  <segmented>0</segmented>
  <object>
    <name>4</name>
    <occluded>0</occluded>
    <bndbox>
      <xmin>352.27</xmin>
      <ymin>437.93</ymin>
      <xmax>385.23</xmax>
      <ymax>462.74</ymax>
    </bndbox>
  </object>
  <object>
    <name>0</name>
    <occluded>0</occluded>
    <bndbox>
      <xmin>363.01</xmin>
      <ymin>499.77</ymin>
      <xmax>394.86</xmax>
      <ymax>524.96</ymax>
    </bndbox>
  </object>
  <object>
    <name>0</name>
    <occluded>0</occluded>
    <bndbox>
      <xmin>356.71</xmin>
      <ymin>469.41</ymin>
      <xmax>392.26</xmax>
      <ymax>493.11</ymax>
    </bndbox>
  </object>
  <object>
    <name>0</name>
    <occluded>0</occluded>
    <bndbox>
      <xmin>343.01</xmin>
      <ymin>516.81</ymin>
      <xmax>358.56</xmax>
      <ymax>529.03</ymax>
    </bndbox>
  </object>
  <object>
    <name>3</name>
    <occluded>0</occluded>
    <bndbox>
      <xmin>347.45</xmin>
      <ymin>378.3</ymin>
      <xmax>375.97</xmax>
      <ymax>403.86</ymax>
    </bndbox>
  </object>
  <object>
    <name>3</name>
    <occluded>0</occluded>
    <bndbox>
      <xmin>344.86</xmin>
      <ymin>347.56</ymin>
      <xmax>373.01</xmax>
      <ymax>372.38</ymax>
    </bndbox>
  </object>
  <object>
    <name>2</name>
    <occluded>0</occluded>
    <bndbox>
      <xmin>344.17</xmin>
      <ymin>528.11</ymin>
      <xmax>360.53</xmax>
      <ymax>538.91</ymax>
    </bndbox>
  </object>
  <object>
    <name>7</name>
    <occluded>0</occluded>
    <bndbox>
      <xmin>348.37</xmin>
      <ymin>410.09</ymin>
      <xmax>377.99</xmax>
      <ymax>434.47</ymax>
    </bndbox>
  </object>
  <object>
    <name>odometer</name>
    <occluded>0</occluded>
    <bndbox>
      <xmin>340.95</xmin>
      <ymin>341.36</ymin>
      <xmax>408.85</xmax>
      <ymax>537.3</ymax>
    </bndbox>
  </object>
</annotation>
